{"stats":{"minecraft:custom":{"minecraft:time_since_rest":8082,"minecraft:play_time":8082,"minecraft:sprint_one_cm":377707,"minecraft:damage_taken":90,"minecraft:walk_one_cm":3269,"minecraft:mob_kills":6,"minecraft:drop":4,"minecraft:jump":61028,"minecraft:leave_game":1,"minecraft:time_since_death":8082,"minecraft:total_world_time":9332,"minecraft:damage_resisted":6636,"minecraft:fall_one_cm":3180,"minecraft:fly_one_cm":1582001},"minecraft:mined":{"minecraft:grass_block":1},"minecraft:dropped":{"minecraft:netherite_boots":1,"minecraft:netherite_leggings":1,"minecraft:netherite_chestplate":1,"minecraft:netherite_helmet":1},"minecraft:killed":{"minecraft:iron_golem":1,"minecraft:zombie":1,"minecraft:slime":1,"minecraft:villager":1,"minecraft:wither":2},"minecraft:used":{"minecraft:bow":40,"minecraft:golden_carrot":29},"minecraft:picked_up":{"minecraft:netherite_boots":1,"minecraft:slime_ball":6,"minecraft:netherite_helmet":1,"minecraft:wither_rose":5,"minecraft:iron_ingot":9,"minecraft:poppy":3,"minecraft:netherite_chestplate":1,"minecraft:netherite_leggings":1,"minecraft:dirt":259,"minecraft:egg":1}},"DataVersion":3105}